symbiosis/__init__.py
symbiosis/cli.py
symbiosis/catalog/__init__.py
symbiosis/filters/__init__.py
symbiosis/projects/__init__.py
symbiosis/providers/__init__.py
symbiosis/server/__init__.py
sybmiosis_gateway-0.1.0.dev1.dist-info/METADATA
sybmiosis_gateway-0.1.0.dev1.dist-info/WHEEL
sybmiosis_gateway-0.1.0.dev1.dist-info/entry_points.txt
sybmiosis_gateway-0.1.0.dev1.dist-info/licenses/LICENSE
sybmiosis_gateway-0.1.0.dev1.dist-info/RECORD
