Metadata-Version: 2.4
Name: sybmiosis-gateway
Version: 0.1.0.dev1
Summary: An open-source AI gateway
License-File: LICENSE
Classifier: Development Status :: 1 - Planning
Classifier: Framework :: FastAPI
Classifier: License :: OSI Approved :: MIT License
Classifier: Programming Language :: Python :: 3.13
Requires-Python: >=3.13
Requires-Dist: fastapi-healthchecks>=1.1.0
Requires-Dist: fastapi>=0.121.0
Requires-Dist: prometheus-fastapi-instrumentator>=7.1.0
Requires-Dist: sqlmodel>=0.0.27
Requires-Dist: typer>=0.20.0
Requires-Dist: uvicorn>=0.38.0
